{
  "Division": "SUPERMARKETS",
  "StoreNo": "2521",
  "Name": "Lutwyche",
  "AddressLine1": "543 Lutwyche Road",
  "AddressLine2": null,
  "Suburb": "Lutwyche",
  "State": "QLD",
  "Postcode": "4030",
  "Latitude": "-27.422652",
  "Longitude": "153.034549",
  "GeoLevel": "0",
  "Distance": null,
  "Phone": "07 3513 4435",
  "GMTZone": "10:0",
  "IsOpen": true,
  "PartnerUrl": null,
  "TradingHours": [
    {
      "Day": "Today",
      "OpenHour": "9:00 AM - 6:00 PM",
      "TradingHourForDisplay": "Sun: 0900-1800"
    },
    {
      "Day": "Tomorrow",
      "OpenHour": "7:00 AM - 9:00 PM",
      "TradingHourForDisplay": "Mon: 0700-2100"
    },
    {
      "Day": "Tuesday",
      "OpenHour": "7:00 AM - 9:00 PM",
      "TradingHourForDisplay": "Tue: 0700-2100"
    },
    {
      "Day": "Wednesday",
      "OpenHour": "7:00 AM - 9:00 PM",
      "TradingHourForDisplay": "Wed: 0700-2100"
    },
    {
      "Day": "Thursday",
      "OpenHour": "7:00 AM - 9:00 PM",
      "TradingHourForDisplay": "Thu: 0700-2100"
    },
    {
      "Day": "Friday",
      "OpenHour": "7:00 AM - 9:00 PM",
      "TradingHourForDisplay": "Fri: 0700-2100"
    },
    {
      "Day": "Saturday",
      "OpenHour": "7:00 AM - 9:00 PM",
      "TradingHourForDisplay": "Sat: 0700-2100"
    },
    {
      "Day": "Sunday",
      "OpenHour": "9:00 AM - 6:00 PM",
      "TradingHourForDisplay": "Sun: 0900-1800"
    }
  ],
  "Facilities": [
    "Direct to boot - drive through",
    "Pick up",
    "Seafood"
  ],
  "CategorisedFacilities": [],
  "NearbyPartners": []
}