{
  "Division": "SUPERMARKETS",
  "StoreNo": "4333",
  "Name": "Victoria Park",
  "AddressLine1": "Victoria Park Central, 366 Albany Highway",
  "AddressLine2": null,
  "Suburb": "Victoria Park",
  "State": "WA",
  "Postcode": "6100",
  "Latitude": "-31.9736546",
  "Longitude": "115.8984471",
  "GeoLevel": "0",
  "Distance": null,
  "Phone": "(08) 6318 9975",
  "GMTZone": "8:0",
  "IsOpen": true,
  "PartnerUrl": null,
  "TradingHours": [
    {
      "Day": "Today",
      "OpenHour": "8:00 AM - 9:00 PM",
      "TradingHourForDisplay": "Thu: 0800-2100"
    },
    {
      "Day": "Tomorrow",
      "OpenHour": "8:00 AM - 9:00 PM",
      "TradingHourForDisplay": "Fri: 0800-2100"
    },
    {
      "Day": "Saturday",
      "OpenHour": "8:00 AM - 5:00 PM",
      "TradingHourForDisplay": "Sat: 0800-1700"
    },
    {
      "Day": "Sunday",
      "OpenHour": "11:00 AM - 5:00 PM",
      "TradingHourForDisplay": "Sun: 1100-1700"
    },
    {
      "Day": "Monday",
      "OpenHour": "8:00 AM - 9:00 PM",
      "TradingHourForDisplay": "Mon: 0800-2100"
    },
    {
      "Day": "Tuesday",
      "OpenHour": "8:00 AM - 9:00 PM",
      "TradingHourForDisplay": "Tue: 0800-2100"
    },
    {
      "Day": "Wednesday",
      "OpenHour": "8:00 AM - 9:00 PM",
      "TradingHourForDisplay": "Wed: 0800-2100"
    },
    {
      "Day": "Thursday",
      "OpenHour": "8:00 AM - 9:00 PM",
      "TradingHourForDisplay": "Thu: 0800-2100"
    }
  ],
  "Facilities": [
    "Direct to boot - drive through",
    "Pick up",
    "Quiet Hour: Mon-Thurs 10:30am"
  ],
  "CategorisedFacilities": [],
  "NearbyPartners": [
    {
      "Division": "BIGW",
      "StoreNo": "450",
      "Name": "BIG W Belmont",
      "AddressLine1": "Abernethy Street and Wright Street",
      "AddressLine2": null,
      "Suburb": "Cloverdale",
      "State": "WA",
      "Postcode": "6105",
      "Latitude": "-31.966726",
      "Longitude": "115.932884",
      "GeoLevel": "0",
      "Distance": "3.39",
      "Phone": "1300 411 875",
      "GMTZone": "8:0",
      "IsOpen": true,
      "PartnerUrl": "https://www.bigw.com.au/store/0450/BIG-W-Cloverdale?utm_source=woolworths&utm_medium=referral&utm_campaign=trafficOrch&utm_content=store_locator_details",
      "TradingHours": [
        {
          "Day": "Today",
          "OpenHour": "8:00 AM - 9:00 PM",
          "TradingHourForDisplay": "Thu: 0800-2100"
        },
        {
          "Day": "Tomorrow",
          "OpenHour": "8:00 AM - 8:00 PM",
          "TradingHourForDisplay": "Fri: 0800-2000"
        },
        {
          "Day": "Saturday",
          "OpenHour": "8:00 AM - 5:00 PM",
          "TradingHourForDisplay": "Sat: 0800-1700"
        },
        {
          "Day": "Sunday",
          "OpenHour": "11:00 AM - 5:00 PM",
          "TradingHourForDisplay": "Sun: 1100-1700"
        },
        {
          "Day": "Monday",
          "OpenHour": "8:00 AM - 8:00 PM",
          "TradingHourForDisplay": "Mon: 0800-2000"
        },
        {
          "Day": "Tuesday",
          "OpenHour": "8:00 AM - 8:00 PM",
          "TradingHourForDisplay": "Tue: 0800-2000"
        },
        {
          "Day": "Wednesday",
          "OpenHour": "8:00 AM - 8:00 PM",
          "TradingHourForDisplay": "Wed: 0800-2000"
        },
        {
          "Day": "Thursday",
          "OpenHour": "8:00 AM - 9:00 PM",
          "TradingHourForDisplay": "Thu: 0800-2100"
        }
      ],
      "Facilities": [
        "Bike Build",
        "In-Store Layby",
        "Party",
        "Pick Up",
        "Soda Stream Refill"
      ],
      "CategorisedFacilities": [],
      "NearbyPartners": null
    }
  ]
}