{
  "Division": "EG",
  "StoreNo": "93918",
  "Name": "Springvale",
  "AddressLine1": "102 Police Road",
  "AddressLine2": null,
  "Suburb": "Springvale",
  "State": "VIC",
  "Postcode": "3171",
  "Latitude": "-37.9348",
  "Longitude": "145.1679",
  "GeoLevel": "0",
  "Distance": null,
  "Phone": "03 4311 1927",
  "GMTZone": "10:0",
  "IsOpen": true,
  "PartnerUrl": null,
  "TradingHours": [
    {
      "Day": "Today",
      "OpenHour": "24 Hours",
      "TradingHourForDisplay": "Sun: 24 Hours"
    },
    {
      "Day": "Tomorrow",
      "OpenHour": "24 Hours",
      "TradingHourForDisplay": "Mon: 24 Hours"
    },
    {
      "Day": "Tuesday",
      "OpenHour": "24 Hours",
      "TradingHourForDisplay": "Tue: 24 Hours"
    },
    {
      "Day": "Wednesday",
      "OpenHour": "24 Hours",
      "TradingHourForDisplay": "Wed: 24 Hours"
    },
    {
      "Day": "Thursday",
      "OpenHour": "24 Hours",
      "TradingHourForDisplay": "Thu: 24 Hours"
    },
    {
      "Day": "Friday",
      "OpenHour": "24 Hours",
      "TradingHourForDisplay": "Fri: 24 Hours"
    },
    {
      "Day": "Saturday",
      "OpenHour": "24 Hours",
      "TradingHourForDisplay": "Sat: 24 Hours"
    },
    {
      "Day": "Sunday",
      "OpenHour": "24 Hours",
      "TradingHourForDisplay": "Sun: 24 Hours"
    }
  ],
  "Facilities": [
    "Rewards-Everyday Rewards",
    "Rewards-Redeem Fuel Discount"
  ],
  "CategorisedFacilities": [
    {
      "Category": "Rewards",
      "CategoryLabel": "Rewards",
      "Facilities": [
        "Everyday Rewards",
        "Redeem Fuel Discount"
      ]
    }
  ],
  "NearbyPartners": [
    {
      "Division": "BIGW",
      "StoreNo": "399",
      "Name": "BIG W Waverley Gardens",
      "AddressLine1": "Police Road and Jackson's Road",
      "AddressLine2": null,
      "Suburb": "Mulgrave",
      "State": "VIC",
      "Postcode": "3170",
      "Latitude": "-37.93484992",
      "Longitude": "145.1895423",
      "GeoLevel": "0",
      "Distance": "1.89",
      "Phone": "1300 411 875",
      "GMTZone": "10:0",
      "IsOpen": true,
      "PartnerUrl": "https://www.bigw.com.au/store/0399/BIG-W-Mulgrave?utm_source=woolworths&utm_medium=referral&utm_campaign=trafficOrch&utm_content=store_locator_details",
      "TradingHours": [
        {
          "Day": "Today",
          "OpenHour": "9:00 AM - 6:00 PM",
          "TradingHourForDisplay": "Sun: 0900-1800"
        },
        {
          "Day": "Tomorrow",
          "OpenHour": "8:00 AM - 7:00 PM",
          "TradingHourForDisplay": "Mon: 0800-1900"
        },
        {
          "Day": "Tuesday",
          "OpenHour": "8:00 AM - 7:00 PM",
          "TradingHourForDisplay": "Tue: 0800-1900"
        },
        {
          "Day": "Wednesday",
          "OpenHour": "8:00 AM - 7:00 PM",
          "TradingHourForDisplay": "Wed: 0800-1900"
        },
        {
          "Day": "Thursday",
          "OpenHour": "8:00 AM - 9:00 PM",
          "TradingHourForDisplay": "Thu: 0800-2100"
        },
        {
          "Day": "Friday",
          "OpenHour": "8:00 AM - 9:00 PM",
          "TradingHourForDisplay": "Fri: 0800-2100"
        },
        {
          "Day": "Saturday",
          "OpenHour": "8:00 AM - 6:00 PM",
          "TradingHourForDisplay": "Sat: 0800-1800"
        },
        {
          "Day": "Sunday",
          "OpenHour": "9:00 AM - 6:00 PM",
          "TradingHourForDisplay": "Sun: 0900-1800"
        }
      ],
      "Facilities": [
        "Bike Build",
        "In-Store Layby",
        "Pick Up",
        "Soda Stream Refill"
      ],
      "CategorisedFacilities": [],
      "NearbyPartners": null
    }
  ]
}